{
  "canisters": {
    "sample_project_backend": {
      "main": "src/sample_project_backend/main.mo",
      "type": "motoko"
    },
    "sample_project_frontend": {
      "dependencies": [
        "sample_project_backend"
      ],
      "source": [
        "src/sample_project_frontend/dist"
      ],
      "type": "assets",
      "workspace": "sample_project_frontend"
    }
  },
  "defaults": {
    "build": {
      "args": "",
      "packtool": ""
    }
  },
  "output_env_file": ".env",
  "version": 1
}